[{"senderKeyId":1738925319,"senderChainKey":{"iteration":2721,"seed":"DBryyTbFjyOudBj3FO4es4rPVDF839Jkf62zsI2Kwxg="},"senderSigningKey":{"public":"BVEvT7rAp4yCVMze+R6E+Ms/IcFHhbHE+2aozP+yHoUs"},"senderMessageKeys":[{},{},{},{},{},{},{},{},{},{},{},{},{},{},{},{},{},{},{},{},{},{},{},{},{},{},{},{},{},{},{},{},{},{},{},{},{},{},{},{},{},{},{},{},{},{},{},{},{},{},{},{},{},{},{},{},{},{},{},{},{},{},{},{},{},{},{},{},{},{},{},{},{},{},{},{},{},{},{},{},{},{},{},{},{},{},{},{},{},{},{},{},{},{},{},{},{},{},{},{},{},{},{},{},{},{},{},{},{},{},{},{},{},{},{},{},{},{},{},{},{},{},{},{},{},{},{},{},{},{},{},{},{},{},{},{},{},{},{},{},{},{},{},{},{},{},{},{},{},{},{},{},{},{},{},{},{},{},{},{},{},{},{},{},{},{},{},{},{},{},{},{},{},{},{},{},{},{},{},{},{},{},{},{},{},{},{},{},{},{},{},{},{},{},{},{},{},{},{},{},{},{},{},{},{},{},{},{},{},{},{},{},{},{},{},{}]},{"senderKeyId":1738925319,"senderChainKey":{"iteration":2493,"seed":"g18MrgUBYoltFceScP8aOmc1FgWH9vMQ5BhOM6LEV4c="},"senderSigningKey":{"public":"BVEvT7rAp4yCVMze+R6E+Ms/IcFHhbHE+2aozP+yHoUs"},"senderMessageKeys":[]},{"senderKeyId":1738925319,"senderChainKey":{"iteration":2505,"seed":"jtDN6QVCv4ohNfJxLur3pjo2W+ejbHqH1Vr0PyJs6dk="},"senderSigningKey":{"public":"BVEvT7rAp4yCVMze+R6E+Ms/IcFHhbHE+2aozP+yHoUs"},"senderMessageKeys":[]},{"senderKeyId":1738925319,"senderChainKey":{"iteration":2507,"seed":"PnjEo+1zcVpEaG4NRHprMndDBG39ltUSGrY2EB024cg="},"senderSigningKey":{"public":"BVEvT7rAp4yCVMze+R6E+Ms/IcFHhbHE+2aozP+yHoUs"},"senderMessageKeys":[]},{"senderKeyId":1738925319,"senderChainKey":{"iteration":2597,"seed":"p+rsEO2qMHZEctrZQnWQCdawxg8gDy2EvhhDIx6p6lU="},"senderSigningKey":{"public":"BVEvT7rAp4yCVMze+R6E+Ms/IcFHhbHE+2aozP+yHoUs"},"senderMessageKeys":[]}]