[{"senderKeyId":637210024,"senderChainKey":{"iteration":193,"seed":"7JPoOdHVfurSNF4tcdS2fhQVIoHt95R9JbpLp47iO6k="},"senderSigningKey":{"public":"BTP1zVHWljkO9+Oazjl26JwByPiFxaaUl9ayySbVPhtz"},"senderMessageKeys":[{},{},{},{},{},{},{},{},{},{},{},{},{},{},{},{},{},{},{},{},{},{},{},{},{},{},{},{},{},{},{},{},{},{},{},{},{},{},{},{},{},{},{},{},{},{},{},{},{},{},{},{},{},{},{},{},{},{},{},{},{},{},{},{},{},{},{},{},{},{},{},{},{},{},{},{},{},{},{},{},{},{},{},{},{},{},{},{},{},{},{},{},{},{},{},{},{},{},{},{},{},{},{},{},{},{},{},{},{},{},{},{},{},{},{},{},{},{},{},{},{},{},{},{},{},{},{},{},{},{},{},{},{},{},{},{},{},{},{},{}]},{"senderKeyId":637210024,"senderChainKey":{"iteration":41,"seed":"qOaXT90iDFSTxT/yw8cTuW2ILBKiGfUK6T1qbICzRPo="},"senderSigningKey":{"public":"BTP1zVHWljkO9+Oazjl26JwByPiFxaaUl9ayySbVPhtz"},"senderMessageKeys":[]},{"senderKeyId":637210024,"senderChainKey":{"iteration":43,"seed":"xwbomi4+sZGnwh8hGcePR8KaAeGGSCKPsc1w7THSC0U="},"senderSigningKey":{"public":"BTP1zVHWljkO9+Oazjl26JwByPiFxaaUl9ayySbVPhtz"},"senderMessageKeys":[]},{"senderKeyId":1774976435,"senderChainKey":{"iteration":1,"seed":"NZI39WVEyVylBFGYm0wTDvPTi45Mizj0adSpZCu+v/I="},"senderSigningKey":{"public":"BVsTMnV9iCVe+lBnnBP61rucKqH247XEN3oLJA7yCzdM"},"senderMessageKeys":[]},{"senderKeyId":637210024,"senderChainKey":{"iteration":165,"seed":"M3pk7LpHyCJ16n1yLiRo9c/AhmBde+2sXJ/G9hN1bJU="},"senderSigningKey":{"public":"BTP1zVHWljkO9+Oazjl26JwByPiFxaaUl9ayySbVPhtz"},"senderMessageKeys":[]}]