[{"senderKeyId":1673276432,"senderChainKey":{"iteration":2367,"seed":"k/vAOXdo7unPIZWnwsW6Z6O2CzA629wotW5POH5blp8="},"senderSigningKey":{"public":"BR/u6NN1YMGGD03pKnDw5limE5Z8ozb4MPUmgT9T7uUP"},"senderMessageKeys":[{},{},{},{},{},{},{},{},{},{},{},{},{},{},{},{},{},{},{},{},{},{},{},{},{},{},{},{},{},{},{},{},{},{},{},{},{},{},{},{},{},{},{},{},{},{},{},{},{},{},{},{},{},{},{},{},{},{},{},{},{},{},{},{},{},{},{},{},{},{},{},{},{},{},{},{},{},{},{},{},{},{},{},{},{},{},{},{},{},{},{},{},{},{},{},{},{},{},{},{},{},{},{},{},{},{},{},{},{},{},{},{},{},{},{},{},{},{},{},{},{},{},{},{},{},{},{},{},{},{},{},{},{},{},{},{},{},{},{},{},{},{},{},{},{},{},{},{},{},{},{},{},{},{},{},{},{},{},{},{},{},{},{},{},{},{},{},{},{},{},{},{},{},{},{},{},{},{},{},{},{},{},{},{},{},{},{},{},{},{},{},{},{},{},{},{},{},{},{},{},{},{},{},{},{},{},{},{},{},{},{},{},{},{},{},{},{},{},{},{},{},{},{},{},{},{},{},{},{},{},{},{},{},{},{},{},{},{},{},{},{},{},{},{},{},{},{},{},{},{},{},{},{},{},{},{},{},{},{},{},{},{},{},{},{},{},{},{},{},{},{},{},{},{},{},{},{},{},{},{},{},{},{},{},{},{},{},{},{},{},{},{},{},{},{},{},{},{},{},{},{},{},{},{},{},{},{},{},{},{},{},{},{},{},{},{},{},{},{},{},{},{},{},{},{},{},{},{},{},{},{},{},{},{},{},{},{},{},{},{},{},{},{},{},{},{},{},{},{},{},{},{},{},{},{},{},{},{},{},{},{},{},{},{},{},{},{},{},{},{},{},{},{},{},{},{},{},{},{},{},{},{},{},{},{},{},{},{},{},{},{},{},{},{},{},{},{},{},{},{},{},{},{},{},{},{},{},{},{},{},{},{},{},{},{},{},{},{},{},{},{},{},{},{},{},{},{},{},{},{},{},{},{},{},{},{},{},{},{},{},{},{},{},{},{},{},{},{},{},{},{},{},{},{},{},{},{},{},{},{},{},{},{},{},{},{},{},{},{},{},{},{},{},{},{},{},{},{},{},{},{},{},{},{},{},{},{},{},{},{},{},{},{},{},{},{},{},{},{},{},{},{},{},{},{},{},{},{},{},{},{},{},{},{},{},{},{},{},{},{},{}]},{"senderKeyId":1673276432,"senderChainKey":{"iteration":1843,"seed":"cbv9akL0fNYkZwG+aYALi0bud1WziE8HYncCy58FwoI="},"senderSigningKey":{"public":"BR/u6NN1YMGGD03pKnDw5limE5Z8ozb4MPUmgT9T7uUP"},"senderMessageKeys":[]},{"senderKeyId":1673276432,"senderChainKey":{"iteration":1871,"seed":"/aqA7DgZocG+Nx0nz0bS5Q8sOrgI79Ft3KGKM9rwCpc="},"senderSigningKey":{"public":"BR/u6NN1YMGGD03pKnDw5limE5Z8ozb4MPUmgT9T7uUP"},"senderMessageKeys":[]},{"senderKeyId":1673276432,"senderChainKey":{"iteration":2143,"seed":"rqUWQTOSHDfgOrAych5ffPIkJ6WlRRCh5DlBAamSRD8="},"senderSigningKey":{"public":"BR/u6NN1YMGGD03pKnDw5limE5Z8ozb4MPUmgT9T7uUP"},"senderMessageKeys":[]},{"senderKeyId":1673276432,"senderChainKey":{"iteration":2357,"seed":"6l8n2foQzLtznGU6ia3c9iM7WgD1NT3gEpbzRLdTYEU="},"senderSigningKey":{"public":"BR/u6NN1YMGGD03pKnDw5limE5Z8ozb4MPUmgT9T7uUP"},"senderMessageKeys":[]}]