[{"senderKeyId":907563079,"senderChainKey":{"iteration":457,"seed":"20Ff4Z5eZe/VzjCl9wmMIF/Ko6fQngfS0YKgx0/EA0w="},"senderSigningKey":{"public":"BbSz8FLoOJp/oiOpB2LbnW45wxqhnmV6OylE5Wj8GUYt"},"senderMessageKeys":[{},{},{},{},{},{},{},{},{},{},{},{},{},{},{},{},{},{},{},{},{},{},{},{},{},{},{},{},{},{},{},{},{},{},{},{},{},{},{},{},{},{},{},{},{},{},{},{},{},{},{},{},{},{},{},{},{},{},{},{},{},{},{},{},{},{},{},{},{},{},{},{},{},{},{},{},{},{},{},{},{},{},{},{},{},{},{},{},{},{},{},{},{},{},{},{},{},{},{},{},{},{},{},{},{},{},{},{},{},{},{},{},{},{},{},{},{},{},{},{},{},{},{},{},{},{},{},{},{},{},{},{},{},{},{},{},{},{},{},{},{},{},{},{},{},{},{},{},{},{},{},{},{},{},{},{},{},{},{},{},{},{},{},{},{},{},{},{},{},{},{},{},{},{},{},{},{},{},{},{},{},{},{},{},{},{},{},{},{},{},{},{},{},{},{},{},{},{},{},{},{},{},{},{},{},{},{},{},{},{},{},{},{},{},{},{},{},{},{},{},{},{},{},{},{},{},{},{},{},{},{},{},{},{},{},{},{},{},{},{},{},{},{},{},{},{},{},{},{},{},{},{},{},{},{},{},{},{},{},{},{},{},{},{},{},{},{},{},{},{},{},{},{},{},{},{},{},{},{},{},{},{},{},{},{},{},{},{},{},{},{},{},{},{},{},{},{},{},{},{},{},{},{},{},{},{},{},{},{},{},{},{},{},{},{},{},{},{},{},{},{},{},{},{},{},{},{},{},{},{},{},{},{},{},{},{},{},{},{},{},{},{},{},{},{},{},{},{},{},{},{},{},{},{},{},{},{},{},{},{},{},{},{},{},{},{},{},{},{},{},{},{},{},{},{},{},{},{},{},{},{},{},{},{}]},{"senderKeyId":907563079,"senderChainKey":{"iteration":11,"seed":"lq35ZTL0Ou8yvLoPfZTfNi3DHT4y+zE0MQdelZV716A="},"senderSigningKey":{"public":"BbSz8FLoOJp/oiOpB2LbnW45wxqhnmV6OylE5Wj8GUYt"},"senderMessageKeys":[]},{"senderKeyId":907563079,"senderChainKey":{"iteration":269,"seed":"BkZXOOfKBrlohddwxBRPRUlSg01116bViSWDGsO+A9A="},"senderSigningKey":{"public":"BbSz8FLoOJp/oiOpB2LbnW45wxqhnmV6OylE5Wj8GUYt"},"senderMessageKeys":[]},{"senderKeyId":907563079,"senderChainKey":{"iteration":271,"seed":"coDEVdxh+U3odOL++z85uPWiZmooK6w5BwpoDc89Zv8="},"senderSigningKey":{"public":"BbSz8FLoOJp/oiOpB2LbnW45wxqhnmV6OylE5Wj8GUYt"},"senderMessageKeys":[]},{"senderKeyId":907563079,"senderChainKey":{"iteration":329,"seed":"cWxXRq1lNw/+PjaQ+N1CxD8mBu8dxMzDIff18DcGJjc="},"senderSigningKey":{"public":"BbSz8FLoOJp/oiOpB2LbnW45wxqhnmV6OylE5Wj8GUYt"},"senderMessageKeys":[]}]